circle_area_ffwc/__init__.py
circle_area_ffwc-0.1.0.dist-info/METADATA
circle_area_ffwc-0.1.0.dist-info/WHEEL
circle_area_ffwc-0.1.0.dist-info/top_level.txt
circle_area_ffwc-0.1.0.dist-info/RECORD
